setup.py
mongobar/__init__.py
mongobar/__version__.py
mongobar/config.py
mongobar/connection.py
mongobar/exceptions.py
mongobar/mongobar.py
mongobar/utils.py
mongobar.egg-info/PKG-INFO
mongobar.egg-info/SOURCES.txt
mongobar.egg-info/dependency_links.txt
mongobar.egg-info/requires.txt
mongobar.egg-info/top_level.txt
mongobar/data/nouns.txt
mongobar/data/verbs.txt
mongobar/scripts/mongobar