Metadata-Version: 1.1
Name: mongobar
Version: 0.0.13
Summary: MongoDB Backup and Restore manager
Home-page: https://github.com/chrisantonellis/mongobar
Author: Christopher Antonellis
Author-email: christopher.antonellis@gmail.com
License: MIT
Keywords: mongodb backup restore mongodump mongorestore
Platform: UNKNOWN
Classifier: Development Status :: 3 - Alpha
Classifier: Environment :: Console
Classifier: Intended Audience :: Developers
Classifier: License :: OSI Approved :: MIT License
Classifier: Natural Language :: English
Classifier: Programming Language :: Python :: 3
Classifier: Programming Language :: Python :: 3.6
Classifier: Topic :: Database :: Front-Ends
Classifier: Topic :: Software Development
